{
    "version": 3,
    "cmakeMinimumRequired": {
        "major": 3,
        "minor": 21,
        "patch": 0
    },
    "configurePresets": [
        {
            "name": "deb",
            "displayName": "GMake GCC Debug",
            "description": "Generated by Make with GCC base debug preset.",
            "generator": "Unix Makefiles",
            "inherits": [
                "gcc-deb"
            ],
            "cacheVariables": {
                "CMAKE_EXPORT_COMPILE_COMMANDS": "ON",
                "CMAKE_C_STANDARD": "11",
                "CMAKE_C_COMPILER": "gcc-12",
                "CMAKE_BUILD_TYPE": "Debug",
                "CMAKE_RUNTIME_OUTPUT_DIRECTORY": "${sourceDir}/build/deb",
                "CMAKE_C_FLAGS":
                    "-g3 -Wall -Wextra -Wfloat-equal -Wtype-limits -Wpointer-arith -Wshadow -Winit-self -fno-diagnostics-show-option"
            }
        },
        {
            "name": "rel",
            "displayName": "GMake GCC Release",
            "description": "Generated by Make with GCC base release preset.",
            "generator": "Unix Makefiles",
            "inherits": [
                "gcc-rel"
            ],
            "cacheVariables": {
                "CMAKE_EXPORT_COMPILE_COMMANDS": "ON",
                "CMAKE_C_STANDARD": "11",
                "CMAKE_C_COMPILER": "gcc-12",
                "CMAKE_BUILD_TYPE": "Release",
                "CMAKE_RUNTIME_OUTPUT_DIRECTORY": "${sourceDir}/build/rel",
                "CMAKE_C_FLAGS":
                    "-Wall -Wextra -Wfloat-equal -Wtype-limits -Wpointer-arith -Wshadow -Winit-self -fno-diagnostics-show-option"
            }
        }
    ]
}
